thetennisplay/__init__.py
thetennisplay/__main__.py
thetennisplay/court.py
thetennisplay/driver.py
thetennisplay/singleton.py
thetennisplay/skeleton.py
thetennisplay/validators.py
thetennisplay/xpaths.py
thetennisplay-1.0.0.dist-info/LICENSE
thetennisplay-1.0.0.dist-info/METADATA
thetennisplay-1.0.0.dist-info/WHEEL
thetennisplay-1.0.0.dist-info/entry_points.txt
thetennisplay-1.0.0.dist-info/RECORD
