Metadata-Version: 2.1
Name: thetennisplay
Version: 1.0.0
Summary: Automates tennis court reservation checks and notifications
Home-page: https://github.com/jaycho1214/thetennisplay
License: MIT
Author: Jay Cho
Author-email: jaycho1214@gmail.com
Requires-Python: >3.8,<4.0
Classifier: License :: OSI Approved :: MIT License
Classifier: Programming Language :: Python :: 3
Classifier: Programming Language :: Python :: 3.9
Classifier: Programming Language :: Python :: 3.10
Classifier: Programming Language :: Python :: 3.11
Requires-Dist: beautifulsoup4 (>=4.12.2,<5.0.0)
Requires-Dist: chime (>=0.7.0,<0.8.0)
Requires-Dist: rich (>=13.6.0,<14.0.0)
Requires-Dist: schedule (>=1.2.1,<2.0.0)
Requires-Dist: selenium (>=4.14.0,<5.0.0)
Requires-Dist: typer (>=0.9.0,<0.10.0)
Project-URL: Repository, https://github.com/jaycho1214/thetennisplay
